binder_trace
