Metadata-Version: 2.1
Name: my-binder-trace
Version: 1.4.3
Home-page: https://github.com/MartinKayJr/binder-trace
Author: MartinKay
Author-email: martinkay@qq.com
Classifier: License :: OSI Approved :: MIT License
Classifier: Operating System :: OS Independent
Classifier: Programming Language :: Python :: 3.9
Requires-Python: >=3.9
Requires-Dist: hexdump~=3.3
Requires-Dist: frida
Requires-Dist: frida-tools
Requires-Dist: jsonpickle~=2.2.0
Requires-Dist: python-pcapng~=2.1.0
Requires-Dist: pycolors~=0.1.2
Requires-Dist: prompt-toolkit==3.0.41
Requires-Dist: python-ranges
Requires-Dist: pyperclip
Requires-Dist: pytest
Requires-Dist: pytest-cov
